instrMem/instrMem.v
`timescale 1ns/1ps

module instrmem (
    input              clk,
    input      [9:0]   address,      
    output     [31:0]  instruction
);

    reg [7:0] mem [0:1023];          
    reg [31:0] data_reg;
    integer i;  
    
    initial begin
        for (i = 0; i < 1024; i = i + 1) begin
            mem[i] = 8'h00;
        end
        
        mem[0]  = 8'h34;
        mem[1]  = 8'h12;
        mem[2]  = 8'h01;
        mem[3]  = 8'h3C;

        mem[4]  = 8'h78;
        mem[5]  = 8'h56;
        mem[6]  = 8'h22;
        mem[7]  = 8'h34;
        
        mem[8]  = 8'h00;
        mem[9]  = 8'h00;
        mem[10] = 8'h02;
        mem[11] = 8'hAC;
        
        mem[12] = 8'h00;
        mem[13] = 8'h00;
        mem[14] = 8'h03;
        mem[15] = 8'h8C;
        
        mem[16] = 8'h20;
        mem[17] = 8'h18;
        mem[18] = 8'h44;
        mem[19] = 8'h00;
        
        mem[20] = 8'h22;
        mem[21] = 8'h20;
        mem[22] = 8'h85;
        mem[23] = 8'h00;
        
        mem[24] = 8'h28;
        mem[25] = 8'h25;
        mem[26] = 8'h86;
        mem[27] = 8'h00;
        
        mem[28] = 8'h2A;
        mem[29] = 8'h25;
        mem[30] = 8'h87;
        mem[31] = 8'h00;
    end
    
    always @(posedge clk) begin
        data_reg <= {mem[address], mem[address+1], mem[address+2], mem[address+3]};
    end
    
    assign instruction = data_reg;

endmodule

instrMem/instrmem_tb.v
`timescale 1ns/1ps

module instrmem_tb;

    reg         clk;
    reg  [9:0]  address;
    wire [31:0] instruction;
    integer i;  

    instrmem uut (
        .clk        (clk),
        .address    (address),
        .instruction(instruction)
    );

    always #5 clk = ~clk;

    initial begin
        $display("\n========== INSTRUCTION MEMORY TEST ==========\n");
        
        clk = 0;
        address = 0;
        
        for (i = 0; i < 8; i = i + 1) begin
            address = i * 4;
            #10;
            $display("Address %2d: 0x%h", address, instruction);
        end
        
        $display("\n========== TEST COMPLETED ==========");
        #50;
        $finish;
    end

    initial begin
        $dumpfile("instrmem.vcd");
        $dumpvars(0, instrmem_tb);
    end

endmodule

instrMem/instrmem.vcd
$date
	Thu Jul 23 22:31:05 2026
$end
$version
	Icarus Verilog
$end
$timescale
	1ps
$end
$scope module instrmem_tb $end
$var wire 32 ! instruction [31:0] $end
$var reg 10 " address [9:0] $end
$var reg 1 # clk $end
$var integer 32 $ i [31:0] $end
$scope module uut $end
$var wire 10 % address [9:0] $end
$var wire 1 # clk $end
$var wire 32 & instruction [31:0] $end
$var reg 32 ' data_reg [31:0] $end
$var integer 32 ( i [31:0] $end
$upscope $end
$upscope $end
$enddefinitions $end
$comment Show the parameter values. $end
$dumpall
$end
#0
$dumpvars
b10000000000 (
bx '
bx &
b0 %
b0 $
0#
b0 "
bx !
$end
#5000
b110100000100100000000100111100 !
b110100000100100000000100111100 &
b110100000100100000000100111100 '
1#
#10000
0#
b100 "
b100 %
b1 $
#15000
b1111000010101100010001000110100 !
b1111000010101100010001000110100 &
b1111000010101100010001000110100 '
1#
#20000
0#
b1000 "
b1000 %
b10 $
#25000
b1010101100 !
b1010101100 &
b1010101100 '
1#
#30000
0#
b1100 "
b1100 %
b11 $
#35000
b1110001100 !
b1110001100 &
b1110001100 '
1#
#40000
0#
b10000 "
b10000 %
b100 $
#45000
b100000000110000100010000000000 !
b100000000110000100010000000000 &
b100000000110000100010000000000 '
1#
#50000
0#
b10100 "
b10100 %
b101 $
#55000
b100010001000001000010100000000 !
b100010001000001000010100000000 &
b100010001000001000010100000000 '
1#
#60000
0#
b11000 "
b11000 %
b110 $
#65000
b101000001001011000011000000000 !
b101000001001011000011000000000 &
b101000001001011000011000000000 '
1#
#70000
0#
b11100 "
b11100 %
b111 $
#75000
b101010001001011000011100000000 !
b101010001001011000011100000000 &
b101010001001011000011100000000 '
1#
#80000
0#
b1000 $
