ALU/ALU.v
`timescale 1ns/1ps
module ALU (
    input   [31:0]in1,
    input   [31:0]in2,
    input   [2:0]func,
    input   [4:0]shamt,
    output  reg[31:0]out,
    output  reg sign,
    output  reg overflow,
    output  reg zero
);
    always @(*) begin
        overflow = 1'b0;
        case (func)
            3'b000: begin
                 out = in1 + in2; //ADD
                 overflow = (in1[31] && in2[31] && !out[31]) || (!in1[31] && !in2[31] && out[31]);
                 end
            3'b001: begin
                out = in1 - in2; //SUB
                overflow = (in1[31] && !in2[31] && !out[31]) || (!in1[31] && in2[31] && out[31]);
                end
            3'b010: out = in1 >> shamt; //shift right logical
            3'b011: out = in1 << shamt; //shift left logical
            3'b100: out = ~(in1 & in2); //NAND
            3'b101: out = in1<in2? 32'd1 : 32'd0; //set less than
            3'b110: out = in1<in2? in1 : in2; //Minimum
            default: out = 32'd0;
        endcase
        zero = (out == 32'd0) ? 1'b1 : 1'b0;
        sign = out[31];
    end

endmodule

ALU/tb_alu.v
`timescale 1ns/1ps

module tb_ALU();

    reg  [31:0] in1;
    reg  [31:0] in2;
    reg  [2:0]  func;
    reg  [4:0]  shamt;
    wire [31:0] out;
    wire        sign;
    wire        overflow;
    wire        zero;

    ALU uut (
        .in1(in1),
        .in2(in2),
        .func(func),
        .shamt(shamt),
        .out(out),
        .sign(sign),
        .overflow(overflow),
        .zero(zero)
    );

    initial begin
        $dumpfile("alu_test.vcd");
        $dumpvars(0, tb_ALU);

        $monitor("Time=%0t | func=%b | in1=%d | in2=%d | out=%d | zero=%b | ovf=%b", 
                 $time, func, in1, in2, out, zero, overflow);

        func = 3'b000; in1 = 32'd10; in2 = 32'd20; shamt = 5'd0;
        #10;

        func = 3'b001; in1 = 32'd50; in2 = 32'd20;
        #10;

        func = 3'b010; in1 = 32'd16; shamt = 5'd2;
        #10;

        func = 3'b011; in1 = 32'd3; shamt = 5'd3;
        #10;

        func = 3'b100; in1 = 32'hFFFF_0000; in2 = 32'h00FF_00FF;
        #10;

        func = 3'b101; in1 = 32'd15; in2 = 32'd40;
        #10;

        func = 3'b110; in1 = 32'd100; in2 = 32'd45;
        #10;

        func = 3'b001; in1 = 32'd25; in2 = 32'd25;
        #10;

        func = 3'b000; in1 = 32'h7FFF_FFFF; in2 = 32'd1;
        #10;

        $finish;
    end

endmodule

ALU/alu_test.vcd
$date
	Thu Jul 23 13:54:16 2026
$end
$version
	Icarus Verilog
$end
$timescale
	1ps
$end
$scope module tb_ALU $end
$var wire 1 ! zero $end
$var wire 1 " sign $end
$var wire 1 # overflow $end
$var wire 32 $ out [31:0] $end
$var reg 3 % func [2:0] $end
$var reg 32 & in1 [31:0] $end
$var reg 32 ' in2 [31:0] $end
$var reg 5 ( shamt [4:0] $end
$scope module uut $end
$var wire 3 ) func [2:0] $end
$var wire 32 * in1 [31:0] $end
$var wire 32 + in2 [31:0] $end
$var wire 5 , shamt [4:0] $end
$var reg 32 - out [31:0] $end
$var reg 1 # overflow $end
$var reg 1 " sign $end
$var reg 1 ! zero $end
$upscope $end
$upscope $end
$enddefinitions $end
$comment Show the parameter values. $end
$dumpall
$end
#0
$dumpvars
b11110 -
b0 ,
b10100 +
b1010 *
b0 )
b0 (
b10100 '
b1010 &
b0 %
b11110 $
0#
0"
0!
$end
#10000
b110010 &
b110010 *
b1 %
b1 )
#20000
b100 $
b100 -
b10 (
b10 ,
b10000 &
b10000 *
b10 %
b10 )
#30000
b11000 $
b11000 -
b11 (
b11 ,
b11 &
b11 *
b11 %
b11 )
#40000
1"
b11111111000000001111111111111111 $
b11111111000000001111111111111111 -
b111111110000000011111111 '
b111111110000000011111111 +
b11111111111111110000000000000000 &
b11111111111111110000000000000000 *
b100 %
b100 )
#50000
0"
b1 $
b1 -
b101000 '
b101000 +
b1111 &
b1111 *
b101 %
b101 )
#60000
b101101 $
b101101 -
b101101 '
b101101 +
b1100100 &
b1100100 *
b110 %
b110 )
#70000
1!
b0 $
b0 -
b11001 '
b11001 +
b11001 &
b11001 *
b1 %
b1 )
#80000
1"
0!
1#
b10000000000000000000000000000000 $
b10000000000000000000000000000000 -
b1 '
b1 +
b1111111111111111111111111111111 &
b1111111111111111111111111111111 *
b0 %
b0 )
